aind_mri_targeting/__init__.py
aind_mri_targeting/headframe_rotations.py
aind_mri_targeting/implant_rotations.py
aind_mri_targeting/util.py
aind_mri_targeting/scripts/__init__.py
aind_mri_targeting/scripts/calculate_headframe_transforms.py
aind_mri_targeting/scripts/fit_implant.py
aind_mri_targeting/scripts/headframe_centers_of_mass.py
aind_mri_targeting/scripts/install_notebooks.py
aind_mri_targeting-0.1.6.dist-info/licenses/LICENSE
aind_mri_targeting-0.1.6.dist-info/METADATA
aind_mri_targeting-0.1.6.dist-info/WHEEL
aind_mri_targeting-0.1.6.dist-info/entry_points.txt
aind_mri_targeting-0.1.6.dist-info/top_level.txt
aind_mri_targeting-0.1.6.dist-info/RECORD
