Metadata-Version: 2.4
Name: aind-mri-targeting
Version: 0.1.6
Summary: Tools to plan and execute MRI-guided targeting experiments
Author: Allen Institute for Neural Dynamics
Author-email: Galen Lynch <galen@galenlynch.com>, Yoni Browning <yoni.browning@alleninstitute.org>
License-Expression: MIT
Project-URL: Repository, https://github.com/AllenNeuralDynamics/aind-mri-targeting/
Project-URL: Issues, https://github.com/AllenNeuralDynamics/aind-mri-targeting/issues
Project-URL: Changelog, https://github.com/AllenNeuralDynamics/aind-mri-targeting/blob/main/CHANGELOG.md
Classifier: Programming Language :: Python :: 3
Requires-Python: >=3.9
License-File: LICENSE
Requires-Dist: aind-anatomical-utils<0.5,>=0.1
Requires-Dist: aind_mri_utils<2,>=0.10
Requires-Dist: numpy<3,>=1.20
Requires-Dist: pandas<3,>=2
Requires-Dist: pynrrd<2,>=1
Requires-Dist: SimpleITK<3,>=2
Requires-Dist: trimesh[recommend]<5,>=4
Dynamic: license-file
